benchtools.cp310-win_amd64.pyd
BenchTools-2.0.4.dist-info/LICENSE
BenchTools-2.0.4.dist-info/METADATA
BenchTools-2.0.4.dist-info/WHEEL
BenchTools-2.0.4.dist-info/top_level.txt
BenchTools-2.0.4.dist-info/RECORD
