Metadata-Version: 2.1
Name: BenchTools
Version: 2.0.4
Summary: Is an simple bench tool.
Home-page: https://github.com/PothpothBR/benchtools
Author: Bruno Dalagnol
Author-email: dalagnolbruno88@gmail.com
License: MIT
Keywords: benchmark,optimization,bench tools,benchmark tool
Platform: Windows
Platform: Linux
Requires-Python: >=3.0
License-File: LICENSE
